[
  {
    "id": "prod_001",
    "codigo": "RAC001",
    "nome": "Ração Premium Cães Adultos",
    "descricao": "Ração premium para cães adultos, sabor frango",
    "preco_custo": 45.00,
    "preco_venda": 65.00,
    "estoque_minimo": 10,
    "estoque_atual": 25,
    "unidade": "KG",
    "categoria": "Ração",
    "ativo": true,
    "created_at": "2024-01-01T00:00:00.000Z",
    "updated_at": "2024-01-01T00:00:00.000Z"
  },
  {
    "id": "prod_002",
    "codigo": "RAC002",
    "nome": "Ração Premium Gatos Filhotes",
    "descricao": "Ração premium para gatos filhotes, sabor salmão",
    "preco_custo": 38.00,
    "preco_venda": 55.00,
    "estoque_minimo": 8,
    "estoque_atual": 15,
    "unidade": "KG",
    "categoria": "Ração",
    "ativo": true,
    "created_at": "2024-01-01T00:00:00.000Z",
    "updated_at": "2024-01-01T00:00:00.000Z"
  },
  {
    "id": "prod_003",
    "codigo": "BRIN001",
    "nome": "Brinquedo Osso de Borracha",
    "descricao": "Brinquedo resistente para cães de médio e grande porte",
    "preco_custo": 12.00,
    "preco_venda": 18.00,
    "estoque_minimo": 5,
    "estoque_atual": 12,
    "unidade": "UN",
    "categoria": "Brinquedos",
    "ativo": true,
    "created_at": "2024-01-01T00:00:00.000Z",
    "updated_at": "2024-01-01T00:00:00.000Z"
  },
  {
    "id": "prod_004",
    "codigo": "MED001",
    "nome": "Vermífugo para Cães",
    "descricao": "Vermífugo de amplo espectro para cães",
    "preco_custo": 25.00,
    "preco_venda": 35.00,
    "estoque_minimo": 3,
    "estoque_atual": 8,
    "unidade": "UN",
    "categoria": "Medicamentos",
    "ativo": true,
    "created_at": "2024-01-01T00:00:00.000Z",
    "updated_at": "2024-01-01T00:00:00.000Z"
  },
  {
    "id": "prod_005",
    "codigo": "SNK001",
    "nome": "Meguis Pet The Cat Snacks - Frango",
    "descricao": "Snacks premium para gatos sabor frango. Hidratação e fonte de proteínas. 5 sachês de 15g cada.",
    "preco_custo": 8.50,
    "preco_venda": 12.90,
    "estoque_minimo": 20,
    "estoque_atual": 45,
    "unidade": "CX",
    "categoria": "Snacks",
    "ativo": true,
    "imagem": "/images/cat-snacks-frango.jpg",
    "created_at": "2024-01-15T00:00:00.000Z",
    "updated_at": "2024-01-15T00:00:00.000Z"
  },
  {
    "id": "prod_006",
    "codigo": "SNK002",
    "nome": "Meguis Pet The Cat Snacks - Salmão",
    "descricao": "Snacks premium para gatos sabor salmão. Hidratação e fonte de proteínas. 5 sachês de 15g cada.",
    "preco_custo": 9.20,
    "preco_venda": 13.90,
    "estoque_minimo": 20,
    "estoque_atual": 38,
    "unidade": "CX",
    "categoria": "Snacks",
    "ativo": true,
    "imagem": "/images/cat-snacks-salmao.jpg",
    "created_at": "2024-01-15T00:00:00.000Z",
    "updated_at": "2024-01-15T00:00:00.000Z"
  },
  {
    "id": "prod_007",
    "codigo": "SNK003",
    "nome": "Meguis Pet The Cat Snacks - Atum",
    "descricao": "Snacks premium para gatos sabor atum. Hidratação e fonte de proteínas. 5 sachês de 15g cada.",
    "preco_custo": 8.80,
    "preco_venda": 13.50,
    "estoque_minimo": 20,
    "estoque_atual": 42,
    "unidade": "CX",
    "categoria": "Snacks",
    "ativo": true,
    "imagem": "/images/cat-snacks-atum.jpg",
    "created_at": "2024-01-15T00:00:00.000Z",
    "updated_at": "2024-01-15T00:00:00.000Z"
  }
]
